junctionart/draw/__init__.py
junctionart/draw/area.ipynb
junctionart/draw/AreaGeometry.py
junctionart/draw/Color.py
junctionart/draw/draw_intersection.ipynb
junctionart/draw/intersection_drawer_refactor.ipynb
junctionart/draw/IntersectionDrawer.py
junctionart/draw/IntersectionPolygon.py
junctionart/draw/numpy_test.ipynb
junctionart/draw/ODRPlot.py
junctionart/draw/parampoly_draw.ipynb
junctionart/draw/ParamPolyRoadPolygon.py
junctionart/draw/RoadPolygon.py
junctionart/draw/StraightRoadPolygon.py
junctionart/draw/test_10000.ipynb
junctionart/draw/test_intersection.ipynb
junctionart/extensions/__init__.py
junctionart/extensions/CountryCodes.py
junctionart/extensions/ExtendedLane.py
junctionart/extensions/ExtendedLanes.py
junctionart/extensions/ExtendedLaneSection.py
junctionart/extensions/ExtendedOpenDrive.py
junctionart/extensions/ExtendedPlanview.py
junctionart/extensions/ExtendedPredecessor.py
junctionart/extensions/ExtendedRoad.py
junctionart/extensions/ExtendedSpiral.py
junctionart/extensions/ExtendedSuccessor.py
junctionart/extensions/IntertialParamPoly.py
junctionart/extensions/LaneOffset.py
junctionart/extensions/moreHelpers.py
junctionart/extensions/renamedClasses.py
junctionart/extensions/signalManager.py
junctionart/junctions/__init__.py
junctionart/junctions/AngleCurvatureMap.py
junctionart/junctions/ConnectionBuilder.py
junctionart/junctions/CurveRoadBuilder.py
junctionart/junctions/Direction.py
junctionart/junctions/Geometry.py
junctionart/junctions/IncidentPoint.py
junctionart/junctions/Intersection.py
junctionart/junctions/IntersectionValidator.py
junctionart/junctions/JunctionAreaTypes.py
junctionart/junctions/JunctionBuilder.py
junctionart/junctions/JunctionBuilderFromPointsAndHeading.py
junctionart/junctions/JunctionDef.py
junctionart/junctions/JunctionHarvester.py
junctionart/junctions/JunctionMerger.py
junctionart/junctions/LaneBuilder.py
junctionart/junctions/LaneConfiguration.py
junctionart/junctions/LaneConfigurationStrategies.py
junctionart-0.1.2.dist-info/LICENSE
junctionart-0.1.2.dist-info/WHEEL
junctionart-0.1.2.dist-info/METADATA
junctionart-0.1.2.dist-info/RECORD
