Metadata-Version: 2.1
Name: junctionart
Version: 0.1.2
Summary: Procedural HD Map and Intersection Generator
License: Mozilla Public License Version 2.0
Author: Adhocmaster
Author-email: adhocmaster@live.com
Requires-Python: >=3.7.9,<4.0.0
Classifier: License :: Other/Proprietary License
Classifier: Programming Language :: Python :: 3
Classifier: Programming Language :: Python :: 3.8
Classifier: Programming Language :: Python :: 3.9
Classifier: Programming Language :: Python :: 3.10
Requires-Dist: Babel (==2.9.1)
Requires-Dist: Cycler (==0.10.0)
Requires-Dist: Flask (==1.1.2)
Requires-Dist: Jinja2 (==2.11.2)
Requires-Dist: MarkupSafe (==1.1.1)
Requires-Dist: Pillow (==8.0.1)
Requires-Dist: PySocks (==1.7.1)
Requires-Dist: PyYAML (==5.3.1)
Requires-Dist: Pygments (==2.7.3)
Requires-Dist: Send2Trash (==1.5.0)
Requires-Dist: Shapely (==1.7.1)
Requires-Dist: Sphinx (>=4.1.2,<5.0.0)
Requires-Dist: Werkzeug (==1.0.1)
Requires-Dist: alabaster (==0.7.12)
Requires-Dist: argon2-cffi (==20.1.0)
Requires-Dist: astroid (==2.4.2)
Requires-Dist: async_generator (==1.10)
Requires-Dist: atomicwrites (==1.4.0)
Requires-Dist: attrs (==20.3.0)
Requires-Dist: backcall (==0.2.0)
Requires-Dist: bleach (==3.2.1)
Requires-Dist: brotlipy (==0.7.0)
Requires-Dist: certifi (==2021.5.30)
Requires-Dist: cffi (==1.14.4)
Requires-Dist: chardet (==4.0.0)
Requires-Dist: click (==7.1.2)
Requires-Dist: colorama (==0.4.4)
Requires-Dist: cryptography (==3.3.1)
Requires-Dist: decorator (==4.4.2)
Requires-Dist: defusedxml (>=0.7.1,<0.8.0)
Requires-Dist: dill (==0.3.3)
Requires-Dist: docutils (==0.16)
Requires-Dist: entrypoints (==0.3)
Requires-Dist: flake8 (==3.8.4)
Requires-Dist: idna (==2.10)
Requires-Dist: imagesize (==1.2.0)
Requires-Dist: importlib-metadata (==2.0.0)
Requires-Dist: iniconfig (==1.1.1)
Requires-Dist: ipykernel (==5.3.4)
Requires-Dist: ipython (==7.19.0)
Requires-Dist: ipython_genutils (==0.2.0)
Requires-Dist: isort (==5.6.4)
Requires-Dist: itsdangerous (==1.1.0)
Requires-Dist: jedi (==0.17.2)
Requires-Dist: json5 (==0.9.5)
Requires-Dist: jsonschema (==3.2.0)
Requires-Dist: jupyter-client (==6.1.7)
Requires-Dist: jupyter-core (==4.7.0)
Requires-Dist: jupyterlab (==2.2.6)
Requires-Dist: jupyterlab-pygments (==0.1.2)
Requires-Dist: jupyterlab-server (==1.2.0)
Requires-Dist: lazy-object-proxy (==1.4.3)
Requires-Dist: linkify-it-py (>=1.0.1,<2.0.0)
Requires-Dist: markdown-it-py (==1.1.0)
Requires-Dist: matplotlib (==3.3.2)
Requires-Dist: mccabe (==0.6.1)
Requires-Dist: mdit-py-plugins (==0.2.8)
Requires-Dist: methodtools (==0.4.2)
Requires-Dist: mistune (==0.8.4)
Requires-Dist: mkl-service (==2.3.0)
Requires-Dist: more-itertools (==8.6.0)
Requires-Dist: mpmath (==1.1.0)
Requires-Dist: myst-parser (==0.15.1)
Requires-Dist: nbclient (==0.5.1)
Requires-Dist: nbconvert (==6.0.7)
Requires-Dist: nbformat (==5.0.8)
Requires-Dist: nest-asyncio (==1.4.3)
Requires-Dist: notebook (==6.1.4)
Requires-Dist: numpy (==1.20.3)
Requires-Dist: olefile (==0.46)
Requires-Dist: packaging (==20.7)
Requires-Dist: pandas (==1.1.3)
Requires-Dist: pandocfilters (==1.4.3)
Requires-Dist: parso (==0.7.0)
Requires-Dist: pickleshare (==0.7.5)
Requires-Dist: pip (==20.3.1)
Requires-Dist: pluggy (==0.13.1)
Requires-Dist: prometheus-client (==0.9.0)
Requires-Dist: prompt-toolkit (==3.0.8)
Requires-Dist: psutil (>=5.8.0,<6.0.0)
Requires-Dist: py (==1.9.0)
Requires-Dist: pyOpenSSL (==20.0.1)
Requires-Dist: pycodestyle (==2.6.0)
Requires-Dist: pycparser (==2.20)
Requires-Dist: pyflakes (==2.2.0)
Requires-Dist: pylint (==2.6.0)
Requires-Dist: pyparsing (==2.4.7)
Requires-Dist: pyrsistent (==0.17.3)
Requires-Dist: python-dateutil (==2.8.1)
Requires-Dist: pytz (==2020.1)
Requires-Dist: pywin32 (==227)
Requires-Dist: pywinpty (==0.5.7)
Requires-Dist: pyzmq (==20.0.0)
Requires-Dist: requests (==2.25.1)
Requires-Dist: rope (==0.18.0)
Requires-Dist: scikit-spatial (==6.0.1)
Requires-Dist: scipy (==1.5.2)
Requires-Dist: seaborn (==0.11.0)
Requires-Dist: six (==1.15.0)
Requires-Dist: snowballstemmer (==2.1.0)
Requires-Dist: sphinx-rtd-theme (>=0.5.2,<0.6.0)
Requires-Dist: sympy (==1.6.2)
Requires-Dist: tabulate (>=0.8.9,<0.9.0)
Requires-Dist: terminado (==0.9.1)
Requires-Dist: testpath (==0.4.4)
Requires-Dist: toml (==0.10.1)
Requires-Dist: tornado (==6.1)
Requires-Dist: traitlets (==5.0.5)
Requires-Dist: typed-ast (==1.4.1)
Requires-Dist: typing-extensions (==3.10.0.0)
Requires-Dist: urllib3 (==1.26.3)
Requires-Dist: wcwidth (==0.2.5)
Requires-Dist: webencodings (==0.5.1)
Requires-Dist: wheel (==0.36.1)
Requires-Dist: win-inet-pton (==1.1.0)
Requires-Dist: wincertstore (==0.2)
Requires-Dist: wirerope (==0.4.2)
Requires-Dist: wrapt (==1.11.2)
Requires-Dist: z3-solver (==4.8.10.0)
Requires-Dist: zipp (==3.4.0)
